{
    "-pn": "Np",
    "-n1": "Np",
    "_arg1prop-epon_p": "PREP",
    "_or-adv": "ADVdir",
    "bli_pass": "V",
    "_nlxm": "N",
    "_alxm": "ADJ",
    "_vlxm": "V",
    "_pn": "Np",
    "_n1": "Np",
    "_propername-boyfirstname": "Np",
    "_propername-girlfirstname": "Np",
    "_propername-lastname": " Np",
    "_propername-town": " Np",
    "_propername-country": " Np",
    "_propername-fylke": " Np",
    "_propername-kommune": "Np",
    "_clause": "PREP",
    "_atelop": "PREP",
    "_sel": "PREP",
    "_detachposs": "PREP",
    "_advprtcl": "ADV",
    "_partcl": "ADV",
    "_arg1prop-epon-p": "PREP",
    "_prep-vmod-time": "PREP",
    "_prep-nmod-time": "PREP",
    "_prep-plce": "PREP",
    "_prep-modadv-plce": "PREP",
    "hvis_prep-cond": "COMP",
    "av_part-spec-q": "PREP",
    "av_part-spec-card": "PREP",
    "av_part-spec-mass": "PREP",
    "av_part-measure": "PREP",
    "av_part-adj": "PREP",
    "av_part-adj2": "PREP",
    "av_measure": "PREP",
    "med_measure": "PREP",
    "til_poss": "PREP",
    "av_poss": "PREP",
    "for_poss": "PREP",
    "til_expl-dep": "PREP",
    "med_expl-dep": "PREP",
    "som_prep-expl-dep": "PREP",
    "som_prep-s": "PREP",
    "_rais": "PREP",
    "_rais-vmod": "PREP",
    "_rel-p": "PREP",
    "av_agent": "PREP",
    "fra_p-rel": "PREP",
    "mer_cmpar-reg": "ADJ",
    "mest_superlat": "ADJ",
    "mer_vp-mod-cmpar-reg": "ADJ",
    "mest_vp-mod-superlat": "ADJ",
    "mer_cmpar-close": "ADJ",
    "mer_cmpar-close-with-cmpar": "ADJ",
    "mere_cmpar-reg": "ADJ",
    "mere_cmpar-close": "ADJ",
    "mere_cmpar-close-with-cmpar": "ADJ",
    "mindre_cmpar-reg": "ADJ",
    "minst_superlat": "ADJ",
    "mindre_vp-mod-cmpar-reg": "ADJ",
    "minst_vp-mod-superlat": "ADJ",
    "mindre_cmpar-close": "ADJ",
    "mindre_cmpar-close-with-cmpar": "ADJ",
    "enn_cmpardep-reg": "PRT",
    "som_cmpardep-reg": "PRT",
    "enn_cmpardiff-n": "PRT",
    "som_cmpareq-n": "PRT",
    "enn_cmpardep-close": "PRT",
    "like": "ADV",
    "for": "ADV",
    "likedan-som_equalzr": "ADJ",
    "slik-som_equalzr": "ADJ",
    "egen_masc-weak": "ADJ",
    "eget_neut-weak": "ADJ",
    "ikke_s-adv": "ADVneg",
    "slettes-ikke_s-adv": "ADVneg",
    "slett-ikke_s-adv": "ADVneg",
    "overhodet-ikke_s-adv": "ADVneg",
    "ikke-lenger_s-adv": "ADVneg",
    "ikke-lengre_s-adv": "ADVneg",
    "ei_s-adv": "ADVneg",
    "egentlig_s-adv": "ADV",
    "neppe_s-adv": "ADVneg",
    "iallfall_s-adv": "ADV",
    "heller_s-adv": "ADV",
    "helst_s-adv": "ADV",
    "likeledes_s-adv": "ADV",
    "likeså_s-adv": "ADV",
    "likså_s-adv": "ADV",
    "herved_s-adv": "ADV",
    "ergo_s-adv": "ADV",
    "sannsynligvis_s-adv": "ADV",
    "virkelig_s-adv": "ADV",
    "antakeligvis_s-adv": "ADV",
    "antageligvis_s-adv": "ADV",
    "nødvendigvis_s-adv": "ADV",
    "antydningsvis_s-adv": "ADV",
    "antagelig_s-adv": "ADV",
    "antakelig_s-adv": "ADV",
    "trolig_s-adv": "ADV",
    "endatil_s-adv": "ADV",
    "attpåtil_s-adv": "ADV",
    "endog_s-adv": "ADV",
    "kanskje_s-adv": "ADV",
    "mon_s-adv": "ADV",
    "mon-tro_s-adv": "ADV",
    "må-tro_s-adv": "ADV",
    "må-tru_s-adv": "ADV",
    "så_s-adv": "ADV",
    "aldri_s-adv": "ADVneg",
    "aldri-noensinne_s-adv": "ADVneg",
    "noensinne_s-adv": "ADV",
    "muligens_s-adv": "ADV",
    "muligvis_s-adv": "ADV",
    "riktignok_s-adv": "ADV",
    "hittil_s-adv": "ADV",
    "alltid_s-adv": "ADV",
    "sjelden_s-adv": "ADV",
    "tidligere_s-adv": "ADV",
    "ofte_s-adv": "ADV",
    "nylig_s-adv": "ADV",
    "jevnlig_s-adv": "ADV",
    "noen-ganger_s-adv": "ADV",
    "heldigvis_s-adv": "ADV",
    "eksempelvis_s-adv": "ADV",
    "for-eksempel-dot_s-adv": "ADV",
    "for-eksempel-dot-dot_s-adv": "ADV",
    "for-eksempel_s-adv": "ADV",
    "nettopp_s-adv": "ADV",
    "akkurat_s-adv": "ADV",
    "altså_s-adv": "ADV",
    "uansett_s-adv": "ADV",
    "fremdeles_s-adv": "ADV",
    "forhåpentlig_s-adv": "ADV",
    "forhåpentligvis_s-adv": "ADV",
    "også_s-adv": "ADV",
    "følgelig_s-adv": "ADV",
    "forresten_s-adv": "ADV",
    "fortrinnsvis_s-adv": "ADV",
    "for-resten_s-adv": "ADV",
    "faktisk_s-adv": "ADV",
    "for-så-vidt_s-adv": "ADV",
    "just_s-adv": "ADV",
    "nemlig_s-adv": "ADV",
    "igjen_s-adv": "ADV",
    "likevel_s-adv": "ADV",
    "naturligvis_s-adv": "ADV",
    "selvfølgelig_s-adv": "ADV",
    "selvsagt_s-adv": "ADV",
    "allikevel_s-adv": "ADV",
    "forøvrig_s-adv": "ADV",
    "for-øvrig_s-adv": "ADV",
    "vel_s-adv": "ADV",
    "derfor_s-adv": "ADV",
    "gjerne_s-adv": "ADV",
    "alternativt_s-adv": "ADV",
    "dessverre_s-adv": "ADV",
    "dessuten_s-adv": "ADV",
    "dernest_s-adv": "ADV",
    "derimot_s-adv": "ADV",
    "tydeligvis_s-adv": "ADV",
    "nok_s-adv": "ADV",
    "ellers_s-adv": "ADV",
    "deriblant_s-adv": "ADV",
    "engang_s-adv": "ADV",
    "for-det-meste_s-adv": "ADV",
    "videre_s-adv": "ADV",
    "deretter_s-adv": "ADV",
    "halvveis_s-adv": "ADV",
    "imidlertid_s-adv": "ADV",
    "dog_s-adv": "ADV",
    "istedet_s-adv": "ADV",
    "i-stedet_s-adv": "ADV",
    "isteden_s-adv": "ADV",
    "ingenlunde_s-adv": "ADV",
    "dermed_s-adv": "ADV",
    "slik_s-adv": "ADV",
    "_m-adv": "ADVm",
    "_adv": "ADV",
    "_regadv": "ADV",
    "selv_refl": "ADVm",
    "sjølv_refl": "ADVm",
    "sjøl_refl": "ADVm",
    "sjæl_refl": "ADVm",
    "hvor_wh-regadv": "ADVplc",
    "hvori_wh-regadv": "ADV",
    "hvoriblant_wh-regadv": "ADVplc",
    "hvo_wh-regadv": "ADVplc",
    "når_wh-regadv": "ADVtemp",
    "hvorfor_wh-regadv": "ADV",
    "hvi_wh-regadv": "ADV",
    "hvordan_wh-regadv": "ADVm",
    "hvorledes_wh-regadv": "ADVm",
    "kossen_wh-regadv": "ADVm",
    "åssen_wh-regadv": "ADVm",
    "korsen_wh-regadv": "ADVm",
    "hvor_wh-orientadv": "ADVplc",
    "hvortil_wh-orientadv": "ADVplc",
    "hvor-til_wh-orientadv": "ADVplc",
    "hvorhen_wh-orientadv": "ADVplc",
    "hvorimot_wh-orientadv": "ADVplc",
    "hvor-hen_wh-orientadv": "ADVplc",
    "hvorfra_wh-orientadv": "ADVplc",
    "hvor-fra_wh-orientadv": "ADVplc",
    "hvoretter_wh-orientadv": "ADVplc",
    "hvorav_wh-regadv": "ADV",
    "hvormed_wh-regadv": "ADV",
    "hvorom_wh-regadv": "ADV",
    "hvorpå_wh-regadv": "ADV",
    "hvorvidt_wh-regadv": "ADV",
    "å_inf-comp": "PRTinf",
    "å_arb-inf-comp": "PRTinf",
    "at_subord": "COMP",
    "det_subord": "PN",
    "som-om_subord": "PREP",
    "som_subord": "PREP",
    "likesom_subord": "PREP",
    "liksom_subord": "PREP",
    "om_y-n-subord": "COMP",
    "hvorvidt_subord": "COMP",
    "best-som__prep-time": "ADVtemp",
    "dersom_comp": "COMP",
    "enskjønt_comp": "COMP",
    "ennskjønt_comp": "COMP",
    "omennskjønt_comp": "COMP",
    "uaktet_comp": "COMP",
    "etter_som_comp": "COMP",
    "ettersom_comp": "COMP",
    "best-som_comp": "COMP",
    "for_at_comp": "COMP",
    "forat_comp": "COMP",
    "fordi_comp": "COMP",
    "for-di_comp": "COMP",
    "for_comp": "COMP",
    "siden_comp": "COMP",
    "før-enn_prep-time": "PREPtemp",
    "førenn_prep-time": "PREPtemp",
    "i_fall_comp": "COMP",
    "i_allfall_comp": "ADV",
    "i_alle_fall_comp": "ADV",
    "ifall_comp": "COMP",
    "i_hvertfall_comp": "ADV",
    "i_hvert_fall_comp": "ADV",
    "hvertfall_comp": "ADV",
    "idet__prep-time": "COMP",
    "i-det__prep-time": "COMP",
    "med-mindre_comp": "COMP",
    "om-enn_comp": "COMP",
    "mens_prep-time": "COMP",
    "imens_prep-time": "ADVtemp",
    "om_comp_cond": "COMP",
    "omenn_comp": "COMP",
    "omenskjønt_comp": "COMP",
    "selv_om_comp": "COMP",
    "sjøl_om_comp": "COMP",
    "skjønt_comp": "COMP",
    "så_framt_comp": "COMP",
    "så_fremt_comp": "COMP",
    "såframt_comp": "COMP",
    "såfremt_comp": "COMP",
    "viss_comp": "COMP",
    "som_fillerrelpron": "PNrel",
    "hvilket_fillerrelpron": "PNrel",
    "som_subjrelpron": "PNrel",
    "hvilket_subjrelpron": "PNrel",
    "som_subjgap": "PN",
    "for_anse-for-å": "COMP",
    "som-om_adj-pred-clse": "PREP",
    "som_adj-pred-clse": "PREP",
    "som_stille-som-n": "PREP",
    "som_synes-som-a": "PREP",
    "-comma": "PUN",
    "-parenthesis": "PUN",
    "-quotation": "PUN",
    "-bracket": "PUN",
    "-curlybracket": "PUN",
    "-angledbracket": "PUN",
    "period": "PUN",
    "period-interjct": "PUN",
    "quest-mark": "PUN",
    "quest-interjct": "PUN",
    "exclam-mark": "PUN",
    "period-n": "PUN",
    "period-adj-or-adv": "PUN",
    "period-prep": "PUN",
    "quest-noun": "PUN",
    "exclam-noun": "PUN",
    "quest-prep": "PUN",
    "exclam-prep": "PUN",
    "quest-adj-or-adv": "PUN",
    "exclam-adj-or-adv": "PUN",
    "colon": "PUN",
    "semicolon": "PUN",
    "gedankenstrech": "PUN",
    "slash": "PUN",
    "_n-connect-symb": "PUN",
    "_p-adv-connect": "PUN",
    "_p-adv-dir-connect": "PUN",
    "_interject-connect": "PUN",
    "_connect": "PUN",
    "_a-connect": "PUN",
    "_v-connect": "PUN",
    "_n-connect": "PUN",
    "_corrconnect": "PUN",
    "_perspron": "PN",
    "han_perspron-acc": "PN",
    "meg_refl": "PNrefl",
    "oss_refl": "PNrefl",
    "deg_refl": "PNrefl",
    "dere_refl": "PNrefl",
    "seg_refl": "PNrefl",
    "hverandre_recip": "PNrec  NEW",
    "hinannen_recip": "PNrec",
    "_pre-poss": "PNposs",
    "_post-poss": "PNposs",
    "hvis_3-quest-poss": "PNposs",
    "hvis_3-rel-poss": "PNposs",
    "_refl-preposs": "PNposs",
    "_refl-postposs": "PNposs",
    "sin_possparticle": "PNposs",
    "si_possparticle": "PNposs",
    "sitt_possparticle": "PNposs",
    "sine_possparticle": "PNposs",
    "s_possparticle": "PRTposs",
    "quote_possparticle": "PRTposs",
    "hvem_interrpron": "Wh",
    "hva_interrpron": "Wh",
    "hvor_interrpron": "Wh",
    "når_interrpron": "Wh",
    "det_expl": "PN",
    "den_def-art": "ART",
    "det_def-art": "ART",
    "de_def-art": "ART",
    "_dem": "DEM",
    "en_indef-art": "ART",
    "et_indef-art": "ART",
    "ei_indef-art": "ART",
    "_card": "CARD",
    "_card-dig": "CARD",
    "ene_card-weak": "CARD",
    "klokka_det": "PRT",
    "klokken_det": "PRT",
    "kl_det": "PRT",
    "kl_period_det": "PRT",
    "anno_det": "PRT",
    "nummer_det": "PRT",
    "nr-dot_det": "PRT",
    "nr_det": "PRT",
    "_ordinal": "ORD",
    "dot_ordinal": "ORD",
    "samme_dem": "DEM",
    "samme_def-q": "DEM",
    "samme_adj": "ADJ",
    "mange_adj": "ADJ",
    "få_adj": "ADJ",
    "flere_cmpar-count": "QUANT",
    "færre_cmpar-count": "QUANT",
    "mer_cmpar-mass3": "QUANT",
    "mer_cmpar-mass": "QUANT",
    "mindre_cmpar-mass": "QUANT",
    "mer_cmpar-mass2": "QUANT",
    "mindre_cmpar-mass2": "QUANT",
    "flest_superlat-str-count": "QUANT",
    "flest_superlat-post-count": "QUANT",
    "færrest_superlat-str-count": "QUANT",
    "mest_superlat-str-mass": "QUANT",
    "minst_superlat-str-mass": "QUANT",
    "fleste_superlat-wk-count": "QUANT",
    "færreste_superlat-wk-count": "QUANT",
    "meste_superlat-wk-mass": "QUANT",
    "minste_superlat-wk-mass": "QUANT",
    "ingen_indef-quant-pl": "QUANT",
    "ingen_indef-quant-sg": "QUANT",
    "intet_indef-quant-sg": "QUANT",
    "mang-en_indef-quant-sg": "QUANT",
    "mangt-et_indef-quant-sg": "QUANT",
    "mangt_indef-quant-sg": "QUANT",
    "ingenting_indef-quant-sg": "QUANT",
    "hver_indef-quant-sg": "QUANT",
    "enhver_indef-quant-sg": "QUANT",
    "annenhver_indef-quant-sg": "QUANT",
    "annethvert_indef-quant-sg": "QUANT",
    "hvert_indef-quant-sg": "QUANT",
    "ethvert_indef-quant-sg": "QUANT",
    "noen_indef-quant-pl": "QUANT",
    "somme_indef-quant-pl": "QUANT",
    "noe_indef-quant-sg": "QUANT",
    "somt_indef-quant-sg": "QUANT",
    "noe_degcmpar": "QUANT",
    "enkelte_indef-quant-pl": "QUANT",
    "mange_indef-quant-pl": "QUANT",
    "ørten_indef-quant-pl": "QUANT",
    "få_indef-quant-pl": "QUANT",
    "flere_indef-quant-pl": "QUANT",
    "flere_indef-cmpar-quant-pl": "QUANT",
    "færre_indef-cmpar-quant-pl": "QUANT",
    "litt_indef-quant-sg": "QUANT",
    "noe_indef-quant2-sg": "QUANT",
    "mye_modble": "QUANT",
    "mye_modble-abs": "QUANT",
    "mye_indef-quant-sg": "QUANT",
    "bitte-lite-grann_indef-quant-sg": "QUANT",
    "_degrpos": "ADV",
    "_degpos": "ADV",
    "_wh-degpos": "ADV",
    "_degcmpar": "ADV",
    "_cardspec": "ADV",
    "ikke_qualadv": "ADVneg",
    "ikke_focqualadv": "ADVneg",
    "nesten_qualifadv": "ADV",
    "selv_focqualadv": "ADV",
    "bare_focqualadv": "ADV",
    "til-og-med_focqualadv": "ADV",
    "lite_modble": "QUANT",
    "lite__indef-quant-sg": "QUANT",
    "nok_indef-quant-sg": "QUANT",
    "alle_indef-quant-pl": "QUANT",
    "all_indef-quant-sg": "QUANT",
    "alt_indef-quant-sg": "QUANT",
    "allting_indef-quant-sg": "QUANT",
    "hva_som_helst-quant-sg": "QUANT",
    "begge_indef-quant-pl": "QUANT",
    "samtlige_indef-quant-pl": "QUANT",
    "hvilke_interr-quant": "QUANT",
    "hvilken_interr-quant": "QUANT",
    "hvilket_interr-quant": "QUANT",
    "alle_defquant-pl": "QUANT",
    "all_defquant-sg": "QUANT",
    "hele_defquant-sg": "QUANT",
    "alt_defquant-sg": "QUANT",
    "begge_defquant-pl": "QUANT",
    "all_defquant-sg-poss": "QUANT",
    "hele_defquant-sg-poss": "QUANT",
    "alt_defquant-sg-poss": "QUANT",
    "alle_defquant-pl-poss": "QUANT",
    "begge_defquant-pl-poss": "QUANT",
    "_interj": "INTRJCT",
    "_dirtel-end-p": "PREPdir",
    "_dirtel-beg-p": "PREPdir",
    "_dirtel-via-p": "PREPdir",
    "_advmod-dirtel-end-p": "PREPdir",
    "_advmod-dirtel-beg-p": "PREPdir",
    "_advmod-dirtel-via-p": "PREPdir",
    "_nondelim-fix": "PREPtemp",
    "_time-p": "PREPtemp",
    "_diratel-p": "PREPdir",
    "_advmod-diratel-p": "PREPdir",
    "_reg-p-loc": "PREPplc",
    "_advmod-reg-p-loc": "PREPplc",
    "_reg-p-tmp": "PREPtemp",
    "_reg-p": "PREP",
    "_reg-p-tmp-weekday": "PREPtemp",
    "_reg-p-tmp-daytime": "PREPtemp",
    "_reg-p-tmp-disttofuture": "PREPtemp",
    "_reg-adv": "ADV",
    "_reg-adv-loc": "ADV",
    "_dirtel-adv": "ADVdir",
    "_dirtel-p": "PREP",
    "_dirtel-mod-adv": "ADVdir",
    "_orient-adv": "ADVdir",
    "_time-adv": "ADVtemp",
    "_adv-temp": "ADVtemp",
    "_pathtelic-fix": "PREPtemp",
    "_pathatelic-fix": "PREPtemp",
    "_dir-padv-p": "PREP"
}
